ctdd/__init__.py
ctdd/__main__.py
ctdd/ffi_factory.py
ctdd/mocker.py
ctdd/tester.py
ctdd/tester_state.py
ctdd-0.0.7.dist-info/LICENSE
ctdd-0.0.7.dist-info/METADATA
ctdd-0.0.7.dist-info/WHEEL
ctdd-0.0.7.dist-info/RECORD
