Metadata-Version: 2.1
Name: ctdd
Version: 0.0.7
Summary: C test-driven development framework implemented in Python
Home-page: https://github.com/wideopensource/ctdd
Author: WideOpenTech
Author-email: fossie@wideopentech.co.uk
Requires-Python: >=3.8,<4.0
Classifier: License :: OSI Approved :: MIT License
Classifier: Operating System :: OS Independent
Classifier: Programming Language :: Python :: 3
Classifier: Programming Language :: Python :: 3.8
Classifier: Programming Language :: Python :: 3.9
Classifier: Programming Language :: Python :: 3.10
Classifier: Programming Language :: Python :: 3.11
Classifier: Programming Language :: Python :: 3
Requires-Dist: crelm (>=0.0.33,<0.0.34)
Requires-Dist: john (>=0.1.5,<0.2.0)
Project-URL: Repository, https://github.com/wideopensource/ctdd
